[
{
"id": "3157e45d-13d1-4407-8ed2-9b286dced2f4",
"name": "Crossbeam Ventures",
"domain": "crossbeam.vc",
"website": "https://crossbeam.vc",
"industry": null,
"city": null,
"state": null
},
{
"id": "0ed5ca19-381e-40be-b65e-59aad7473edc",
"name": "DCM",
"domain": null,
"website": null,
"industry": null,
"city": null,
"state": null
},
{
"id": "deb6b3d7-fbf3-418d-b805-5037964d4bbe",
"name": "Divergent",
"domain": null,
"website": null,
"industry": null,
"city": null,
"state": null
},
{
"id": "12a64679-033b-4836-8752-120b815ced01",
"name": "Dynamo Ventures",
"domain": null,
"website": null,
"industry": null,
"city": null,
"state": null
},
{
"id": "eaf6557f-58e1-4e2e-9daf-dd3024128191",
"name": "Ebay Ventures",
"domain": null,
"website": null,
"industry": null,
"city": null,
"state": null
},
{
"id": "9dfb9f7f-87f8-4f95-b8b8-9b41f5a44246",
"name": "Elysian Park",
"domain": null,
"website": null,
"industry": null,
"city": null,
"state": null
},
{
"id": "2b673bc8-7b8c-4305-9ea4-afb9d5a9ecb4",
"name": "Entrepreneurs First",
"domain": null,
"website": null,
"industry": null,
"city": null,
"state": null
},
{
"id": "a9c7d780-3a8d-4d5c-9e8d-d19957745aae",
"name": "Equal Ventures",
"domain": null,
"website": null,
"industry": null,
"city": null,
"state": null
},
{
"id": "d7f6076f-6d91-464f-9074-7e1f700f6aae",
"name": "Essence VC",
"domain": null,
"website": null,
"industry": null,
"city": null,
"state": null
},
{
"id": "9d291484-da73-417d-a491-f45280837175",
"name": "Evercore",
"domain": null,
"website": null,
"industry": null,
"city": null,
"state": null
},
{
"id": "529b9778-f83a-434c-a278-5db948517ced",
"name": "Ex Ante",
"domain": null,
"website": null,
"industry": null,
"city": null,
"state": null
},
{
"id": "2d61d1f3-b725-4bd8-a5a2-04abd1c9481d",
"name": "Exponent Capital",
"domain": null,
"website": null,
"industry": null,
"city": null,
"state": null
}
]